vmshepherd/__init__.py
vmshepherd/__main__.py
vmshepherd/app.py
vmshepherd/errors.py
vmshepherd/utils.py
vmshepherd/worker.py
vmshepherd/drivers/__init__.py
vmshepherd/healthcheck/__init__.py
vmshepherd/healthcheck/abstract.py
vmshepherd/healthcheck/dummy_healthcheck.py
vmshepherd/healthcheck/http_healthcheck.py
vmshepherd/http/__init__.py
vmshepherd/http/rpc_api.py
vmshepherd/http/static/css/bootstrap-theme.css
vmshepherd/http/static/css/bootstrap-theme.css.map
vmshepherd/http/static/css/bootstrap-theme.min.css
vmshepherd/http/static/css/bootstrap.css
vmshepherd/http/static/css/bootstrap.css.map
vmshepherd/http/static/css/bootstrap.min.css
vmshepherd/http/static/css/dashboard.css
vmshepherd/http/static/fonts/glyphicons-halflings-regular.eot
vmshepherd/http/static/fonts/glyphicons-halflings-regular.svg
vmshepherd/http/static/fonts/glyphicons-halflings-regular.ttf
vmshepherd/http/static/fonts/glyphicons-halflings-regular.woff
vmshepherd/http/static/js/bootstrap.js
vmshepherd/http/static/js/bootstrap.min.js
vmshepherd/http/static/js/jquery.min.js
vmshepherd/http/templates/index.html.jinja2
vmshepherd/http/templates/preset.html.jinja2
vmshepherd/iaas/__init__.py
vmshepherd/iaas/abstract.py
vmshepherd/iaas/dummy_driver.py
vmshepherd/iaas/openstack_driver.py
vmshepherd/iaas/vm.py
vmshepherd/presets/__init__.py
vmshepherd/presets/abstract.py
vmshepherd/presets/directory_driver.py
vmshepherd/presets/gitrepo_driver.py
vmshepherd/presets/preset.py
vmshepherd/runtime/__init__.py
vmshepherd/runtime/abstract.py
vmshepherd/runtime/inmemory_driver.py
vmshepherd-1.6.4.dist-info/LICENSE
vmshepherd-1.6.4.dist-info/METADATA
vmshepherd-1.6.4.dist-info/WHEEL
vmshepherd-1.6.4.dist-info/dependency_links.txt
vmshepherd-1.6.4.dist-info/entry_points.txt
vmshepherd-1.6.4.dist-info/top_level.txt
vmshepherd-1.6.4.dist-info/RECORD
