Metadata-Version: 2.1
Name: vmshepherd
Version: 1.6.4
Summary: Cluster manager
Home-page: https://github.com/Dreamlab/vmshepherd
Author: Dreamlab - PaaS KRK
Author-email: paas-support@dreamlab.pl
License: UNKNOWN
Keywords: cluster,preset,iaas,cloud,openstack,nova,aws,amazon,ec2
Platform: UNKNOWN
Classifier: Programming Language :: Python :: 3.6
Classifier: Programming Language :: Python :: 3.7
Classifier: Operating System :: POSIX
Requires-Dist: aiofiles (>=0.3.2)
Requires-Dist: aiohttp (<4.0.0,>=3.0.0)
Requires-Dist: aiohttp-jinja2 (>=1.0.0)
Requires-Dist: aiohttp-jsonrpc (>=0.1.0)
Requires-Dist: AsyncOpenStackClient (==0.8.1)
Requires-Dist: aiounittest (>=1.1.0)
Requires-Dist: bidict (>=0.17.2)
Requires-Dist: pyyaml
Requires-Dist: idna (==2.6)
